[
  {"videoId": "dQw4w9WgXcQ", "title": "Rick Astley - Never Gonna Give You Up"},
  {"videoId": "oHg5SJYRHA0", "title": "RickRoll'D"},
  {"videoId": "9bZkp7q19f0", "title": "PSY - GANGNAM STYLE (강남스타일) M/V"},
  {"videoId": "ZZ5LpwO-An4", "title": "HEYYEYAAEYAAAEYAEYAA"},
  {"videoId": "JGwWNGJdvx8", "title": "Ed Sheeran - Shape of You"},
  {"videoId": "kJQP7kiw5Fk", "title": "Luis Fonsi - Despacito ft. Daddy Yankee"},
  {"videoId": "OPf0YbXqDm0", "title": "Mark Ronson - Uptown Funk ft. Bruno Mars"},
  {"videoId": "xvFZjo5PgG0", "title": "Nirvana - Smells Like Teen Spirit"},
  {"videoId": "kXYiU_JCYtU", "title": "Linkin Park - Numb"},
  {"videoId": "eVTXPUF4Oz4", "title": "Linkin Park - In The End"},
  {"videoId": "fJ9rUzIMcZQ", "title": "Queen - Bohemian Rhapsody"},
  {"videoId": "DLzxrzFCyOs", "title": "Rick Astley - Never Gonna Give You Up"},
  {"videoId": "YQHsXMglC9A", "title": "Adele - Hello"},
  {"videoId": "hLQl3WQQoQ0", "title": "Adele - Someone Like You"},
  {"videoId": "04854XqcfCY", "title": "Queen - We Are The Champions"},
  {"videoId": "mWRsgZuwf_8", "title": "Eminem - Lose Yourself"},
  {"videoId": "nfWlot6h_JM", "title": "Taylor Swift - Shake It Off"},
  {"videoId": "2vjPBrBU-TM", "title": "Sia - Chandelier"},
  {"videoId": "09R8_2nJtjg", "title": "Maroon 5 - Sugar"},
  {"videoId": "fRh_vgS2dFE", "title": "Justin Bieber - Sorry"}
]
